cli/__init__.py
cli/main.py
cli/entities/__init__.py
cli/entities/app.py
cli/entities/bitrise.py
cli/entities/fcm.py
cli/entities/git.py
cli/entities/lokalise.py
cli/entities/menu.py
cli/entities/setting.py
cli/form/__init__.py
cli/form/_form_confirm.py
cli/form/bitrise/__init__.py
cli/form/bitrise/branch_form.py
cli/form/bitrise/build_type_form.py
cli/form/bitrise/release_notes_form.py
cli/form/bitrise/version_code_form.py
cli/form/bitrise/version_name_form.py
cli/form/code_gen/__init__.py
cli/form/code_gen/code_gen_form.py
cli/form/code_gen/create_new_module.py
cli/form/code_gen/create_new_screen.py
cli/form/fcm/__init__.py
cli/form/fcm/fcm_firebase_id_form.py
cli/form/fcm/fcm_notification_action_form.py
cli/form/fcm/fcm_notification_body_form.py
cli/form/fcm/fcm_notification_deeplink_form.py
cli/form/fcm/fcm_notification_title_form.py
cli/form/git/__init__.py
cli/form/git/_new_branch_form.py
cli/form/git/_pull_request_form.py
cli/form/git/create_new_branch.py
cli/form/git/create_new_pull_request.py
cli/form/git/git_form.py
cli/form/lokalise/__init__.py
cli/form/lokalise/lokalise_add_strings_form.py
cli/form/lokalise/lokalise_get_strings_form.py
cli/form/lokalise/lokalise_menu_form.py
cli/utils/__init__.py
cli/utils/configs.py
cli/utils/editor.py
cli/utils/shell.py
cli/utils/singleton.py
cli/utils/ui.py
cli/utils/ui_menu.py
cli/utils/code_templates/__init__.py
cli/utils/code_templates/module/__init__.py
cli/utils/code_templates/module/build_gradle_template.py
cli/utils/code_templates/module/consumer_rules_pro_template.py
cli/utils/code_templates/module/git_ignore_tempate.py
cli/utils/code_templates/module/manifest_template.py
cli/utils/code_templates/module/navigation_template.py
cli/utils/code_templates/module/proguard_rules_pro_template.py
cli/utils/code_templates/module/update_app_gradle.py
cli/utils/code_templates/module/update_navigation_home.py
cli/utils/code_templates/module/update_settings_gradle.py
cli/utils/code_templates/screen/__init__.py
android_cli-1.18.2.dist-info/METADATA
android_cli-1.18.2.dist-info/WHEEL
android_cli-1.18.2.dist-info/entry_points.txt
android_cli-1.18.2.dist-info/top_level.txt
android_cli-1.18.2.dist-info/RECORD
