Metadata-Version: 2.4
Name: android-cli
Version: 1.18.2
Requires-Dist: questionary
Requires-Dist: requests
Requires-Dist: python-lokalise-api
Requires-Dist: prompt_toolkit
Requires-Dist: google-cloud-firestore
Requires-Dist: google-auth
Dynamic: requires-dist
